vibium_darwin_x64/__init__.py
vibium_darwin_x64/bin/clicker
vibium_darwin_x64-0.1.4.dist-info/METADATA
vibium_darwin_x64-0.1.4.dist-info/WHEEL
vibium_darwin_x64-0.1.4.dist-info/licenses/LICENSE
vibium_darwin_x64-0.1.4.dist-info/licenses/NOTICE
vibium_darwin_x64-0.1.4.dist-info/RECORD
